CHANGES.rst
LICENSE
MANIFEST.in
README.rst
setup.py
saraswati/__init__.py
saraswati/cli.py
saraswati/model.py
saraswati/recorder.py
saraswati/uploader.py
saraswati/util.py
saraswati.egg-info/PKG-INFO
saraswati.egg-info/SOURCES.txt
saraswati.egg-info/dependency_links.txt
saraswati.egg-info/entry_points.txt
saraswati.egg-info/not-zip-safe
saraswati.egg-info/requires.txt
saraswati.egg-info/top_level.txt
saraswati/setup/__init__.py
saraswati/setup/systemd/__init__.py
saraswati/setup/systemd/saraswati.default
saraswati/setup/systemd/saraswati.service